matemagica/__init__.py
matemagica/operacoes.py
matemagica-0.0.1.dist-info/METADATA
matemagica-0.0.1.dist-info/WHEEL
matemagica-0.0.1.dist-info/top_level.txt
matemagica-0.0.1.dist-info/RECORD
