Metadata-Version: 2.1
Name: matemagica
Version: 0.0.1
Summary: Used to perform some math operations more intuitively
Home-page: https://github.com/lborgatow/dio_bootcamps/tree/main/Gera%C3%A7%C3%A3o%20Tech%20Unimed-BH%20-%20Ci%C3%AAncia%20de%20Dados/matemagica-package
Author: Leonardo
Author-email: 
License: UNKNOWN
Platform: UNKNOWN
Requires-Python: >=3.8
